__init__.py
main.py
git_heatmap-0.0.6.dist-info/LICENSE
git_heatmap-0.0.6.dist-info/METADATA
git_heatmap-0.0.6.dist-info/WHEEL
git_heatmap-0.0.6.dist-info/entry_points.txt
git_heatmap-0.0.6.dist-info/top_level.txt
git_heatmap-0.0.6.dist-info/RECORD
